<?xml version="1.0" standalone="no"?>
<?xml-stylesheet type="text/xsl" href="file:///C:/Program Files/Analog Devices/VisualDSP 5.0/System/linker_log.xsl"?>
<DOCUMENT gen_time='Fri Nov 06 10:26:00 2015
'>
<MSG id='02080690' mid='li2050' type='Warning' suppressed=''>
<TEXT><![CDATA[Symbol '_btowc' is defined in more than one library.
        Defined in:     libio532y.dlb[widechar.doj]
        Redefined in:   libc532y.dlb[btowc.doj]
        Definition from libio532y.dlb[widechar.doj] will be used.]]></TEXT>
</MSG>
<MSG id='02081CB0' mid='li2050' type='Warning' suppressed=''>
<TEXT><![CDATA[Symbol '_clearerr' is defined in more than one library.
        Defined in:     libio532y.dlb[clearerr.doj]
        Redefined in:   libc532y.dlb[clearerr.doj]
        Definition from libio532y.dlb[clearerr.doj] will be used.]]></TEXT>
</MSG>
<MSG id='02082530' mid='li2050' type='Warning' suppressed=''>
<TEXT><![CDATA[Symbol '_fclose' is defined in more than one library.
        Defined in:     libio532y.dlb[fclose.doj]
        Redefined in:   libc532y.dlb[fclose.doj]
        Definition from libio532y.dlb[fclose.doj] will be used.]]></TEXT>
</MSG>
<MSG id='02082658' mid='li2050' type='Warning' suppressed=''>
<TEXT><![CDATA[Symbol '_feof' is defined in more than one library.
        Defined in:     libio532y.dlb[eof.doj]
        Redefined in:   libc532y.dlb[feof.doj]
        Definition from libio532y.dlb[eof.doj] will be used.]]></TEXT>
</MSG>
<MSG id='02082A10' mid='li2050' type='Warning' suppressed=''>
<TEXT><![CDATA[Symbol '_ferror' is defined in more than one library.
        Defined in:     libio532y.dlb[ferror.doj]
        Redefined in:   libc532y.dlb[ferror.doj]
        Definition from libio532y.dlb[ferror.doj] will be used.]]></TEXT>
</MSG>
<MSG id='02082C18' mid='li2050' type='Warning' suppressed=''>
<TEXT><![CDATA[Symbol '_fflush' is defined in more than one library.
        Defined in:     libio532y.dlb[fflush.doj]
        Redefined in:   libc532y.dlb[fflush.doj]
        Definition from libio532y.dlb[fflush.doj] will be used.]]></TEXT>
</MSG>
<MSG id='02082E20' mid='li2050' type='Warning' suppressed=''>
<TEXT><![CDATA[Symbol '_fgetc' is defined in more than one library.
        Defined in:     libio532y.dlb[fgetc.doj]
        Redefined in:   libc532y.dlb[fgetc.doj]
        Definition from libio532y.dlb[fgetc.doj] will be used.]]></TEXT>
</MSG>
<MSG id='02083028' mid='li2050' type='Warning' suppressed=''>
<TEXT><![CDATA[Symbol '_fgetpos' is defined in more than one library.
        Defined in:     libio532y.dlb[fgetpos.doj]
        Redefined in:   libc532y.dlb[fgetpos.doj]
        Definition from libio532y.dlb[fgetpos.doj] will be used.]]></TEXT>
</MSG>
<MSG id='02083380' mid='li2050' type='Warning' suppressed=''>
<TEXT><![CDATA[Symbol '_fgets' is defined in more than one library.
        Defined in:     libio532y.dlb[fgets.doj]
        Redefined in:   libc532y.dlb[fgets.doj]
        Definition from libio532y.dlb[fgets.doj] will be used.]]></TEXT>
</MSG>
<MSG id='020834A8' mid='li2050' type='Warning' suppressed=''>
<TEXT><![CDATA[Symbol '_fgetwc' is defined in more than one library.
        Defined in:     libio532y.dlb[widechar.doj]
        Redefined in:   libc532y.dlb[fgetwc.doj]
        Definition from libio532y.dlb[widechar.doj] will be used.]]></TEXT>
</MSG>
<MSG id='02083800' mid='li2050' type='Warning' suppressed=''>
<TEXT><![CDATA[Symbol '_fgetws' is defined in more than one library.
        Defined in:     libio532y.dlb[widechar.doj]
        Redefined in:   libc532y.dlb[fgetws.doj]
        Definition from libio532y.dlb[widechar.doj] will be used.]]></TEXT>
</MSG>
<MSG id='02083B58' mid='li2050' type='Warning' suppressed=''>
<TEXT><![CDATA[Symbol '_fopen' is defined in more than one library.
        Defined in:     libio532y.dlb[fopen.doj]
        Redefined in:   libc532y.dlb[fopen.doj]
        Definition from libio532y.dlb[fopen.doj] will be used.]]></TEXT>
</MSG>
<MSG id='02083C80' mid='li2050' type='Warning' suppressed=''>
<TEXT><![CDATA[Symbol '_fprintf' is defined in more than one library.
        Defined in:     libio532y.dlb[fprintf_32.doj]
        Redefined in:   libc532y.dlb[fprintf32.doj]
        Definition from libio532y.dlb[fprintf_32.doj] will be used.]]></TEXT>
</MSG>
<MSG id='02083FD8' mid='li2050' type='Warning' suppressed=''>
<TEXT><![CDATA[Symbol '__fprintf64' is defined in more than one library.
        Defined in:     libio532y.dlb[fprintf_64.doj]
        Redefined in:   libc532y.dlb[fprintf64.doj]
        Definition from libio532y.dlb[fprintf_64.doj] will be used.]]></TEXT>
</MSG>
<MSG id='02084250' mid='li2050' type='Warning' suppressed=''>
<TEXT><![CDATA[Symbol '_fputc' is defined in more than one library.
        Defined in:     libio532y.dlb[fputc.doj]
        Redefined in:   libc532y.dlb[fputc.doj]
        Definition from libio532y.dlb[fputc.doj] will be used.]]></TEXT>
</MSG>
<MSG id='02084378' mid='li2050' type='Warning' suppressed=''>
<TEXT><![CDATA[Symbol '_fputs' is defined in more than one library.
        Defined in:     libio532y.dlb[fputs.doj]
        Redefined in:   libc532y.dlb[fputs.doj]
        Definition from libio532y.dlb[fputs.doj] will be used.]]></TEXT>
</MSG>
<MSG id='02084580' mid='li2050' type='Warning' suppressed=''>
<TEXT><![CDATA[Symbol '_fputwc' is defined in more than one library.
        Defined in:     libio532y.dlb[widechar.doj]
        Redefined in:   libc532y.dlb[fputwc.doj]
        Definition from libio532y.dlb[widechar.doj] will be used.]]></TEXT>
</MSG>
<MSG id='020848D8' mid='li2050' type='Warning' suppressed=''>
<TEXT><![CDATA[Symbol '_fputws' is defined in more than one library.
        Defined in:     libio532y.dlb[widechar.doj]
        Redefined in:   libc532y.dlb[fputws.doj]
        Definition from libio532y.dlb[widechar.doj] will be used.]]></TEXT>
</MSG>
<MSG id='02084B50' mid='li2050' type='Warning' suppressed=''>
<TEXT><![CDATA[Symbol '_fread' is defined in more than one library.
        Defined in:     libio532y.dlb[fread.doj]
        Redefined in:   libc532y.dlb[fread.doj]
        Definition from libio532y.dlb[fread.doj] will be used.]]></TEXT>
</MSG>
<MSG id='02084CB0' mid='li2050' type='Warning' suppressed=''>
<TEXT><![CDATA[Symbol '_freopen' is defined in more than one library.
        Defined in:     libio532y.dlb[freopen.doj]
        Redefined in:   libc532y.dlb[freopen.doj]
        Definition from libio532y.dlb[freopen.doj] will be used.]]></TEXT>
</MSG>
<MSG id='02085008' mid='li2050' type='Warning' suppressed=''>
<TEXT><![CDATA[Symbol '_fscanf' is defined in more than one library.
        Defined in:     libio532y.dlb[fscanf_32.doj]
        Redefined in:   libc532y.dlb[fscanf32.doj]
        Definition from libio532y.dlb[fscanf_32.doj] will be used.]]></TEXT>
</MSG>
<MSG id='02085280' mid='li2050' type='Warning' suppressed=''>
<TEXT><![CDATA[Symbol '__fscanf64' is defined in more than one library.
        Defined in:     libio532y.dlb[fscanf_64.doj]
        Redefined in:   libc532y.dlb[fscanf64.doj]
        Definition from libio532y.dlb[fscanf_64.doj] will be used.]]></TEXT>
</MSG>
<MSG id='020854F8' mid='li2050' type='Warning' suppressed=''>
<TEXT><![CDATA[Symbol '_fseek' is defined in more than one library.
        Defined in:     libio532y.dlb[fseek.doj]
        Redefined in:   libc532y.dlb[fseek.doj]
        Definition from libio532y.dlb[fseek.doj] will be used.]]></TEXT>
</MSG>
<MSG id='02085620' mid='li2050' type='Warning' suppressed=''>
<TEXT><![CDATA[Symbol '_fsetpos' is defined in more than one library.
        Defined in:     libio532y.dlb[fsetpos.doj]
        Redefined in:   libc532y.dlb[fsetpos.doj]
        Definition from libio532y.dlb[fsetpos.doj] will be used.]]></TEXT>
</MSG>
<MSG id='02085978' mid='li2050' type='Warning' suppressed=''>
<TEXT><![CDATA[Symbol '_ftell' is defined in more than one library.
        Defined in:     libio532y.dlb[ftell.doj]
        Redefined in:   libc532y.dlb[ftell.doj]
        Definition from libio532y.dlb[ftell.doj] will be used.]]></TEXT>
</MSG>
<MSG id='02085AA0' mid='li2050' type='Warning' suppressed=''>
<TEXT><![CDATA[Symbol '_fwide' is defined in more than one library.
        Defined in:     libio532y.dlb[widechar.doj]
        Redefined in:   libc532y.dlb[fwide.doj]
        Definition from libio532y.dlb[widechar.doj] will be used.]]></TEXT>
</MSG>
<MSG id='02085DF8' mid='li2050' type='Warning' suppressed=''>
<TEXT><![CDATA[Symbol '_fwprintf' is defined in more than one library.
        Defined in:     libio532y.dlb[widechar.doj]
        Redefined in:   libc532y.dlb[fwprintf32.doj]
        Definition from libio532y.dlb[widechar.doj] will be used.]]></TEXT>
</MSG>
<MSG id='02086070' mid='li2050' type='Warning' suppressed=''>
<TEXT><![CDATA[Symbol '__fwprintf64' is defined in more than one library.
        Defined in:     libio532y.dlb[widechar.doj]
        Redefined in:   libc532y.dlb[fwprintf64.doj]
        Definition from libio532y.dlb[widechar.doj] will be used.]]></TEXT>
</MSG>
<MSG id='020862E8' mid='li2050' type='Warning' suppressed=''>
<TEXT><![CDATA[Symbol '_fwrite' is defined in more than one library.
        Defined in:     libio532y.dlb[fwrite.doj]
        Redefined in:   libc532y.dlb[fwrite.doj]
        Definition from libio532y.dlb[fwrite.doj] will be used.]]></TEXT>
</MSG>
<MSG id='02086410' mid='li2050' type='Warning' suppressed=''>
<TEXT><![CDATA[Symbol '_fwscanf' is defined in more than one library.
        Defined in:     libio532y.dlb[widechar.doj]
        Redefined in:   libc532y.dlb[fwscanf32.doj]
        Definition from libio532y.dlb[widechar.doj] will be used.]]></TEXT>
</MSG>
<MSG id='02086768' mid='li2050' type='Warning' suppressed=''>
<TEXT><![CDATA[Symbol '__fwscanf64' is defined in more than one library.
        Defined in:     libio532y.dlb[widechar.doj]
        Redefined in:   libc532y.dlb[fwscanf64.doj]
        Definition from libio532y.dlb[widechar.doj] will be used.]]></TEXT>
</MSG>
<MSG id='020869E0' mid='li2050' type='Warning' suppressed=''>
<TEXT><![CDATA[Symbol '_getc' is defined in more than one library.
        Defined in:     libio532y.dlb[getc.doj]
        Redefined in:   libc532y.dlb[getc.doj]
        Definition from libio532y.dlb[getc.doj] will be used.]]></TEXT>
</MSG>
<MSG id='02086B08' mid='li2050' type='Warning' suppressed=''>
<TEXT><![CDATA[Symbol '_getchar' is defined in more than one library.
        Defined in:     libio532y.dlb[getchar.doj]
        Redefined in:   libc532y.dlb[getchar.doj]
        Definition from libio532y.dlb[getchar.doj] will be used.]]></TEXT>
</MSG>
<MSG id='02086E98' mid='li2050' type='Warning' suppressed=''>
<TEXT><![CDATA[Symbol '_gets' is defined in more than one library.
        Defined in:     libio532y.dlb[gets.doj]
        Redefined in:   libc532y.dlb[gets.doj]
        Definition from libio532y.dlb[gets.doj] will be used.]]></TEXT>
</MSG>
<MSG id='02086FC0' mid='li2050' type='Warning' suppressed=''>
<TEXT><![CDATA[Symbol '_getwc' is defined in more than one library.
        Defined in:     libio532y.dlb[widechar.doj]
        Redefined in:   libc532y.dlb[getwc.doj]
        Definition from libio532y.dlb[widechar.doj] will be used.]]></TEXT>
</MSG>
<MSG id='02087318' mid='li2050' type='Warning' suppressed=''>
<TEXT><![CDATA[Symbol '_getwchar' is defined in more than one library.
        Defined in:     libio532y.dlb[widechar.doj]
        Redefined in:   libc532y.dlb[getwchar.doj]
        Definition from libio532y.dlb[widechar.doj] will be used.]]></TEXT>
</MSG>
<MSG id='02088570' mid='li2050' type='Warning' suppressed=''>
<TEXT><![CDATA[Symbol '_mbrlen' is defined in more than one library.
        Defined in:     libio532y.dlb[widechar.doj]
        Redefined in:   libc532y.dlb[mbrlen.doj]
        Definition from libio532y.dlb[widechar.doj] will be used.]]></TEXT>
</MSG>
<MSG id='020887E8' mid='li2050' type='Warning' suppressed=''>
<TEXT><![CDATA[Symbol '_mbrtowc' is defined in more than one library.
        Defined in:     libio532y.dlb[widechar.doj]
        Redefined in:   libc532y.dlb[mbrtowc.doj]
        Definition from libio532y.dlb[widechar.doj] will be used.]]></TEXT>
</MSG>
<MSG id='02088A60' mid='li2050' type='Warning' suppressed=''>
<TEXT><![CDATA[Symbol '_mbsinit' is defined in more than one library.
        Defined in:     libio532y.dlb[widechar.doj]
        Redefined in:   libc532y.dlb[mbsinit.doj]
        Definition from libio532y.dlb[widechar.doj] will be used.]]></TEXT>
</MSG>
<MSG id='02088CD8' mid='li2050' type='Warning' suppressed=''>
<TEXT><![CDATA[Symbol '_mbsrtowcs' is defined in more than one library.
        Defined in:     libio532y.dlb[widechar.doj]
        Redefined in:   libc532y.dlb[mbsrtowc.doj]
        Definition from libio532y.dlb[widechar.doj] will be used.]]></TEXT>
</MSG>
<MSG id='020891F8' mid='li2050' type='Warning' suppressed=''>
<TEXT><![CDATA[Symbol '_printf' is defined in more than one library.
        Defined in:     libio532y.dlb[printf_32.doj]
        Redefined in:   libc532y.dlb[printf32.doj]
        Definition from libio532y.dlb[printf_32.doj] will be used.]]></TEXT>
</MSG>
<MSG id='02089470' mid='li2050' type='Warning' suppressed=''>
<TEXT><![CDATA[Symbol '__printf64' is defined in more than one library.
        Defined in:     libio532y.dlb[printf_64.doj]
        Redefined in:   libc532y.dlb[printf64.doj]
        Definition from libio532y.dlb[printf_64.doj] will be used.]]></TEXT>
</MSG>
<MSG id='02089720' mid='li2050' type='Warning' suppressed=''>
<TEXT><![CDATA[Symbol '_putc' is defined in more than one library.
        Defined in:     libio532y.dlb[putc.doj]
        Redefined in:   libc532y.dlb[putc.doj]
        Definition from libio532y.dlb[putc.doj] will be used.]]></TEXT>
</MSG>
<MSG id='02089848' mid='li2050' type='Warning' suppressed=''>
<TEXT><![CDATA[Symbol '_putchar' is defined in more than one library.
        Defined in:     libio532y.dlb[putchar.doj]
        Redefined in:   libc532y.dlb[putchar.doj]
        Definition from libio532y.dlb[putchar.doj] will be used.]]></TEXT>
</MSG>
<MSG id='02089BA0' mid='li2050' type='Warning' suppressed=''>
<TEXT><![CDATA[Symbol '_puts' is defined in more than one library.
        Defined in:     libio532y.dlb[puts.doj]
        Redefined in:   libc532y.dlb[puts.doj]
        Definition from libio532y.dlb[puts.doj] will be used.]]></TEXT>
</MSG>
<MSG id='02089CC8' mid='li2050' type='Warning' suppressed=''>
<TEXT><![CDATA[Symbol '_putwc' is defined in more than one library.
        Defined in:     libio532y.dlb[widechar.doj]
        Redefined in:   libc532y.dlb[putwc.doj]
        Definition from libio532y.dlb[widechar.doj] will be used.]]></TEXT>
</MSG>
<MSG id='0208A020' mid='li2050' type='Warning' suppressed=''>
<TEXT><![CDATA[Symbol '_putwchar' is defined in more than one library.
        Defined in:     libio532y.dlb[widechar.doj]
        Redefined in:   libc532y.dlb[putwchar.doj]
        Definition from libio532y.dlb[widechar.doj] will be used.]]></TEXT>
</MSG>
<MSG id='0208A2D0' mid='li2050' type='Warning' suppressed=''>
<TEXT><![CDATA[Symbol '_raise' is defined in more than one library.
        Defined in:     libsmall532y.dlb[raise_s.doj]
        Redefined in:   libc532y.dlb[raise.doj]
        Definition from libsmall532y.dlb[raise_s.doj] will be used.]]></TEXT>
</MSG>
<MSG id='0208A698' mid='li2050' type='Warning' suppressed=''>
<TEXT><![CDATA[Symbol '_remove' is defined in more than one library.
        Defined in:     libio532y.dlb[remove.doj]
        Redefined in:   libc532y.dlb[remove.doj]
        Definition from libio532y.dlb[remove.doj] will be used.]]></TEXT>
</MSG>
<MSG id='0208A7C0' mid='li2050' type='Warning' suppressed=''>
<TEXT><![CDATA[Symbol '_rename' is defined in more than one library.
        Defined in:     libio532y.dlb[rename.doj]
        Redefined in:   libc532y.dlb[rename.doj]
        Definition from libio532y.dlb[rename.doj] will be used.]]></TEXT>
</MSG>
<MSG id='0208A9C8' mid='li2050' type='Warning' suppressed=''>
<TEXT><![CDATA[Symbol '_rewind' is defined in more than one library.
        Defined in:     libio532y.dlb[rewind.doj]
        Redefined in:   libc532y.dlb[rewind.doj]
        Definition from libio532y.dlb[rewind.doj] will be used.]]></TEXT>
</MSG>
<MSG id='0208AF80' mid='li2050' type='Warning' suppressed=''>
<TEXT><![CDATA[Symbol '_scanf' is defined in more than one library.
        Defined in:     libio532y.dlb[scanf_32.doj]
        Redefined in:   libc532y.dlb[scanf32.doj]
        Definition from libio532y.dlb[scanf_32.doj] will be used.]]></TEXT>
</MSG>
<MSG id='0208B300' mid='li2050' type='Warning' suppressed=''>
<TEXT><![CDATA[Symbol '__scanf64' is defined in more than one library.
        Defined in:     libio532y.dlb[scanf_64.doj]
        Redefined in:   libc532y.dlb[scanf64.doj]
        Definition from libio532y.dlb[scanf_64.doj] will be used.]]></TEXT>
</MSG>
<MSG id='0208B578' mid='li2050' type='Warning' suppressed=''>
<TEXT><![CDATA[Symbol '_setbuf' is defined in more than one library.
        Defined in:     libio532y.dlb[setbuf.doj]
        Redefined in:   libc532y.dlb[setbuf.doj]
        Definition from libio532y.dlb[setbuf.doj] will be used.]]></TEXT>
</MSG>
<MSG id='0208B7F0' mid='li2050' type='Warning' suppressed=''>
<TEXT><![CDATA[Symbol '_setvbuf' is defined in more than one library.
        Defined in:     libio532y.dlb[setvbuf.doj]
        Redefined in:   libc532y.dlb[setvbuf.doj]
        Definition from libio532y.dlb[setvbuf.doj] will be used.]]></TEXT>
</MSG>
<MSG id='0208BB48' mid='li2050' type='Warning' suppressed=''>
<TEXT><![CDATA[Symbol '_interrupt' is defined in more than one library.
        Defined in:     libsmall532y.dlb[signal_s.doj]
        Redefined in:   libc532y.dlb[signal.doj]
        Definition from libsmall532y.dlb[signal_s.doj] will be used.]]></TEXT>
</MSG>
<MSG id='0208BE10' mid='li2050' type='Warning' suppressed=''>
<TEXT><![CDATA[Symbol '_signal' is defined in more than one library.
        Defined in:     libsmall532y.dlb[signal_s.doj]
        Redefined in:   libc532y.dlb[signal.doj]
        Definition from libsmall532y.dlb[signal_s.doj] will be used.]]></TEXT>
</MSG>
<MSG id='0208C088' mid='li2050' type='Warning' suppressed=''>
<TEXT><![CDATA[Symbol '_snprintf' is defined in more than one library.
        Defined in:     libio532y.dlb[snprintf_32.doj]
        Redefined in:   libc532y.dlb[snprintf32.doj]
        Definition from libio532y.dlb[snprintf_32.doj] will be used.]]></TEXT>
</MSG>
<MSG id='0208C300' mid='li2050' type='Warning' suppressed=''>
<TEXT><![CDATA[Symbol '__snprintf64' is defined in more than one library.
        Defined in:     libio532y.dlb[snprintf_64.doj]
        Redefined in:   libc532y.dlb[snprintf64.doj]
        Definition from libio532y.dlb[snprintf_64.doj] will be used.]]></TEXT>
</MSG>
<MSG id='0208C578' mid='li2050' type='Warning' suppressed=''>
<TEXT><![CDATA[Symbol '_sprintf' is defined in more than one library.
        Defined in:     libio532y.dlb[sprintf_32.doj]
        Redefined in:   libc532y.dlb[sprintf32.doj]
        Definition from libio532y.dlb[sprintf_32.doj] will be used.]]></TEXT>
</MSG>
<MSG id='0208C7F0' mid='li2050' type='Warning' suppressed=''>
<TEXT><![CDATA[Symbol '__sprintf64' is defined in more than one library.
        Defined in:     libio532y.dlb[sprintf_64.doj]
        Redefined in:   libc532y.dlb[sprintf64.doj]
        Definition from libio532y.dlb[sprintf_64.doj] will be used.]]></TEXT>
</MSG>
<MSG id='0208CAA0' mid='li2050' type='Warning' suppressed=''>
<TEXT><![CDATA[Symbol '_sscanf' is defined in more than one library.
        Defined in:     libio532y.dlb[sscanf_32.doj]
        Redefined in:   libc532y.dlb[sscanf32.doj]
        Definition from libio532y.dlb[sscanf_32.doj] will be used.]]></TEXT>
</MSG>
<MSG id='0208CD18' mid='li2050' type='Warning' suppressed=''>
<TEXT><![CDATA[Symbol '__sscanf64' is defined in more than one library.
        Defined in:     libio532y.dlb[sscanf_64.doj]
        Redefined in:   libc532y.dlb[sscanf64.doj]
        Definition from libio532y.dlb[sscanf_64.doj] will be used.]]></TEXT>
</MSG>
<MSG id='0208D430' mid='li2050' type='Warning' suppressed=''>
<TEXT><![CDATA[Symbol '_swprintf' is defined in more than one library.
        Defined in:     libio532y.dlb[widechar.doj]
        Redefined in:   libc532y.dlb[swprintf32.doj]
        Definition from libio532y.dlb[widechar.doj] will be used.]]></TEXT>
</MSG>
<MSG id='0208D6A8' mid='li2050' type='Warning' suppressed=''>
<TEXT><![CDATA[Symbol '__swprintf64' is defined in more than one library.
        Defined in:     libio532y.dlb[widechar.doj]
        Redefined in:   libc532y.dlb[swprintf64.doj]
        Definition from libio532y.dlb[widechar.doj] will be used.]]></TEXT>
</MSG>
<MSG id='0208D920' mid='li2050' type='Warning' suppressed=''>
<TEXT><![CDATA[Symbol '_swscanf' is defined in more than one library.
        Defined in:     libio532y.dlb[widechar.doj]
        Redefined in:   libc532y.dlb[swscanf32.doj]
        Definition from libio532y.dlb[widechar.doj] will be used.]]></TEXT>
</MSG>
<MSG id='0208DB98' mid='li2050' type='Warning' suppressed=''>
<TEXT><![CDATA[Symbol '__swscanf64' is defined in more than one library.
        Defined in:     libio532y.dlb[widechar.doj]
        Redefined in:   libc532y.dlb[swscanf64.doj]
        Definition from libio532y.dlb[widechar.doj] will be used.]]></TEXT>
</MSG>
<MSG id='0208E008' mid='li2050' type='Warning' suppressed=''>
<TEXT><![CDATA[Symbol '_ungetc' is defined in more than one library.
        Defined in:     libio532y.dlb[ungetc.doj]
        Redefined in:   libc532y.dlb[ungetc.doj]
        Definition from libio532y.dlb[ungetc.doj] will be used.]]></TEXT>
</MSG>
<MSG id='0208E130' mid='li2050' type='Warning' suppressed=''>
<TEXT><![CDATA[Symbol '_ungetwc' is defined in more than one library.
        Defined in:     libio532y.dlb[widechar.doj]
        Redefined in:   libc532y.dlb[ungetwc.doj]
        Definition from libio532y.dlb[widechar.doj] will be used.]]></TEXT>
</MSG>
<MSG id='0208EA50' mid='li2050' type='Warning' suppressed=''>
<TEXT><![CDATA[Symbol '_wcstod' is defined in more than one library.
        Defined in:     libio532y.dlb[widechar.doj]
        Redefined in:   libc532y.dlb[v35_wstod.doj]
        Definition from libio532y.dlb[widechar.doj] will be used.]]></TEXT>
</MSG>
<MSG id='0208ECC8' mid='li2050' type='Warning' suppressed=''>
<TEXT><![CDATA[Symbol '_vfprintf' is defined in more than one library.
        Defined in:     libio532y.dlb[vfprintf_32.doj]
        Redefined in:   libc532y.dlb[vfprintf32.doj]
        Definition from libio532y.dlb[vfprintf_32.doj] will be used.]]></TEXT>
</MSG>
<MSG id='0208EF40' mid='li2050' type='Warning' suppressed=''>
<TEXT><![CDATA[Symbol '__vfprintf64' is defined in more than one library.
        Defined in:     libio532y.dlb[vfprintf_64.doj]
        Redefined in:   libc532y.dlb[vfprintf64.doj]
        Definition from libio532y.dlb[vfprintf_64.doj] will be used.]]></TEXT>
</MSG>
<MSG id='0208F1B8' mid='li2050' type='Warning' suppressed=''>
<TEXT><![CDATA[Symbol '_vfwprintf' is defined in more than one library.
        Defined in:     libio532y.dlb[widechar.doj]
        Redefined in:   libc532y.dlb[vfwprint32.doj]
        Definition from libio532y.dlb[widechar.doj] will be used.]]></TEXT>
</MSG>
<MSG id='0208F430' mid='li2050' type='Warning' suppressed=''>
<TEXT><![CDATA[Symbol '__vfwprintf64' is defined in more than one library.
        Defined in:     libio532y.dlb[widechar.doj]
        Redefined in:   libc532y.dlb[vfwprint64.doj]
        Definition from libio532y.dlb[widechar.doj] will be used.]]></TEXT>
</MSG>
<MSG id='0208F6A8' mid='li2050' type='Warning' suppressed=''>
<TEXT><![CDATA[Symbol '_vprintf' is defined in more than one library.
        Defined in:     libio532y.dlb[vprintf_32.doj]
        Redefined in:   libc532y.dlb[vprintf32.doj]
        Definition from libio532y.dlb[vprintf_32.doj] will be used.]]></TEXT>
</MSG>
<MSG id='0208F920' mid='li2050' type='Warning' suppressed=''>
<TEXT><![CDATA[Symbol '__vprintf64' is defined in more than one library.
        Defined in:     libio532y.dlb[vprintf_64.doj]
        Redefined in:   libc532y.dlb[vprintf64.doj]
        Definition from libio532y.dlb[vprintf_64.doj] will be used.]]></TEXT>
</MSG>
<MSG id='0208FB98' mid='li2050' type='Warning' suppressed=''>
<TEXT><![CDATA[Symbol '_vsnprintf' is defined in more than one library.
        Defined in:     libio532y.dlb[vsnprintf_32.doj]
        Redefined in:   libc532y.dlb[vsnprint32.doj]
        Definition from libio532y.dlb[vsnprintf_32.doj] will be used.]]></TEXT>
</MSG>
<MSG id='0208FE10' mid='li2050' type='Warning' suppressed=''>
<TEXT><![CDATA[Symbol '__vsnprintf64' is defined in more than one library.
        Defined in:     libio532y.dlb[vsnprintf_64.doj]
        Redefined in:   libc532y.dlb[vsnprint64.doj]
        Definition from libio532y.dlb[vsnprintf_64.doj] will be used.]]></TEXT>
</MSG>
<MSG id='02090088' mid='li2050' type='Warning' suppressed=''>
<TEXT><![CDATA[Symbol '_vsprintf' is defined in more than one library.
        Defined in:     libio532y.dlb[vsprintf_32.doj]
        Redefined in:   libc532y.dlb[vsprintf32.doj]
        Definition from libio532y.dlb[vsprintf_32.doj] will be used.]]></TEXT>
</MSG>
<MSG id='02090300' mid='li2050' type='Warning' suppressed=''>
<TEXT><![CDATA[Symbol '__vsprintf64' is defined in more than one library.
        Defined in:     libio532y.dlb[vsprintf_64.doj]
        Redefined in:   libc532y.dlb[vsprintf64.doj]
        Definition from libio532y.dlb[vsprintf_64.doj] will be used.]]></TEXT>
</MSG>
<MSG id='02090578' mid='li2050' type='Warning' suppressed=''>
<TEXT><![CDATA[Symbol '_vswprintf' is defined in more than one library.
        Defined in:     libio532y.dlb[widechar.doj]
        Redefined in:   libc532y.dlb[vswprint32.doj]
        Definition from libio532y.dlb[widechar.doj] will be used.]]></TEXT>
</MSG>
<MSG id='020907F0' mid='li2050' type='Warning' suppressed=''>
<TEXT><![CDATA[Symbol '__vswprintf64' is defined in more than one library.
        Defined in:     libio532y.dlb[widechar.doj]
        Redefined in:   libc532y.dlb[vswprint64.doj]
        Definition from libio532y.dlb[widechar.doj] will be used.]]></TEXT>
</MSG>
<MSG id='02090A68' mid='li2050' type='Warning' suppressed=''>
<TEXT><![CDATA[Symbol '_vwprintf' is defined in more than one library.
        Defined in:     libio532y.dlb[widechar.doj]
        Redefined in:   libc532y.dlb[vwprintf32.doj]
        Definition from libio532y.dlb[widechar.doj] will be used.]]></TEXT>
</MSG>
<MSG id='02090CE0' mid='li2050' type='Warning' suppressed=''>
<TEXT><![CDATA[Symbol '__vwprintf64' is defined in more than one library.
        Defined in:     libio532y.dlb[widechar.doj]
        Redefined in:   libc532y.dlb[vwprintf64.doj]
        Definition from libio532y.dlb[widechar.doj] will be used.]]></TEXT>
</MSG>
<MSG id='02090F58' mid='li2050' type='Warning' suppressed=''>
<TEXT><![CDATA[Symbol '_wcrtomb' is defined in more than one library.
        Defined in:     libio532y.dlb[widechar.doj]
        Redefined in:   libc532y.dlb[wcrtomb.doj]
        Definition from libio532y.dlb[widechar.doj] will be used.]]></TEXT>
</MSG>
<MSG id='020911D0' mid='li2050' type='Warning' suppressed=''>
<TEXT><![CDATA[Symbol '_wcscat' is defined in more than one library.
        Defined in:     libio532y.dlb[widechar.doj]
        Redefined in:   libc532y.dlb[wcscat.doj]
        Definition from libio532y.dlb[widechar.doj] will be used.]]></TEXT>
</MSG>
<MSG id='02091480' mid='li2050' type='Warning' suppressed=''>
<TEXT><![CDATA[Symbol '_wcscmp' is defined in more than one library.
        Defined in:     libio532y.dlb[widechar.doj]
        Redefined in:   libc532y.dlb[wcscmp.doj]
        Definition from libio532y.dlb[widechar.doj] will be used.]]></TEXT>
</MSG>
<MSG id='02091730' mid='li2050' type='Warning' suppressed=''>
<TEXT><![CDATA[Symbol '_wcscoll' is defined in more than one library.
        Defined in:     libio532y.dlb[widechar.doj]
        Redefined in:   libc532y.dlb[wcscoll.doj]
        Definition from libio532y.dlb[widechar.doj] will be used.]]></TEXT>
</MSG>
<MSG id='020919A8' mid='li2050' type='Warning' suppressed=''>
<TEXT><![CDATA[Symbol '_wcscpy' is defined in more than one library.
        Defined in:     libio532y.dlb[widechar.doj]
        Redefined in:   libc532y.dlb[wcscpy.doj]
        Definition from libio532y.dlb[widechar.doj] will be used.]]></TEXT>
</MSG>
<MSG id='02091C20' mid='li2050' type='Warning' suppressed=''>
<TEXT><![CDATA[Symbol '_wcscspn' is defined in more than one library.
        Defined in:     libio532y.dlb[widechar.doj]
        Redefined in:   libc532y.dlb[wcscspn.doj]
        Definition from libio532y.dlb[widechar.doj] will be used.]]></TEXT>
</MSG>
<MSG id='02091E98' mid='li2050' type='Warning' suppressed=''>
<TEXT><![CDATA[Symbol '_wcslen' is defined in more than one library.
        Defined in:     libio532y.dlb[widechar.doj]
        Redefined in:   libc532y.dlb[wcslen.doj]
        Definition from libio532y.dlb[widechar.doj] will be used.]]></TEXT>
</MSG>
<MSG id='02092110' mid='li2050' type='Warning' suppressed=''>
<TEXT><![CDATA[Symbol '_wcsncat' is defined in more than one library.
        Defined in:     libio532y.dlb[widechar.doj]
        Redefined in:   libc532y.dlb[wcsncat.doj]
        Definition from libio532y.dlb[widechar.doj] will be used.]]></TEXT>
</MSG>
<MSG id='020923C0' mid='li2050' type='Warning' suppressed=''>
<TEXT><![CDATA[Symbol '_wcsncpy' is defined in more than one library.
        Defined in:     libio532y.dlb[widechar.doj]
        Redefined in:   libc532y.dlb[wcsncpy.doj]
        Definition from libio532y.dlb[widechar.doj] will be used.]]></TEXT>
</MSG>
<MSG id='020926A8' mid='li2050' type='Warning' suppressed=''>
<TEXT><![CDATA[Symbol '_wcsrtombs' is defined in more than one library.
        Defined in:     libio532y.dlb[widechar.doj]
        Redefined in:   libc532y.dlb[wcsrtomb.doj]
        Definition from libio532y.dlb[widechar.doj] will be used.]]></TEXT>
</MSG>
<MSG id='020929C8' mid='li2050' type='Warning' suppressed=''>
<TEXT><![CDATA[Symbol '_wcstol' is defined in more than one library.
        Defined in:     libio532y.dlb[widechar.doj]
        Redefined in:   libc532y.dlb[wcstol.doj]
        Definition from libio532y.dlb[widechar.doj] will be used.]]></TEXT>
</MSG>
<MSG id='02092C78' mid='li2050' type='Warning' suppressed=''>
<TEXT><![CDATA[Symbol '_wcstoul' is defined in more than one library.
        Defined in:     libio532y.dlb[widechar.doj]
        Redefined in:   libc532y.dlb[wcstoul.doj]
        Definition from libio532y.dlb[widechar.doj] will be used.]]></TEXT>
</MSG>
<MSG id='02092F28' mid='li2050' type='Warning' suppressed=''>
<TEXT><![CDATA[Symbol '_wcsxfrm' is defined in more than one library.
        Defined in:     libio532y.dlb[widechar.doj]
        Redefined in:   libc532y.dlb[wcsxfrm.doj]
        Definition from libio532y.dlb[widechar.doj] will be used.]]></TEXT>
</MSG>
<MSG id='020931A0' mid='li2050' type='Warning' suppressed=''>
<TEXT><![CDATA[Symbol '_wctob' is defined in more than one library.
        Defined in:     libio532y.dlb[widechar.doj]
        Redefined in:   libc532y.dlb[wctob.doj]
        Definition from libio532y.dlb[widechar.doj] will be used.]]></TEXT>
</MSG>
<MSG id='020934F8' mid='li2050' type='Warning' suppressed=''>
<TEXT><![CDATA[Symbol '_wmemcmp' is defined in more than one library.
        Defined in:     libio532y.dlb[widechar.doj]
        Redefined in:   libc532y.dlb[wmemcmp.doj]
        Definition from libio532y.dlb[widechar.doj] will be used.]]></TEXT>
</MSG>
<MSG id='02093770' mid='li2050' type='Warning' suppressed=''>
<TEXT><![CDATA[Symbol '_wmemcpy' is defined in more than one library.
        Defined in:     libio532y.dlb[widechar.doj]
        Redefined in:   libc532y.dlb[wmemcpy.doj]
        Definition from libio532y.dlb[widechar.doj] will be used.]]></TEXT>
</MSG>
<MSG id='020939E8' mid='li2050' type='Warning' suppressed=''>
<TEXT><![CDATA[Symbol '_wmemmove' is defined in more than one library.
        Defined in:     libio532y.dlb[widechar.doj]
        Redefined in:   libc532y.dlb[wmemmove.doj]
        Definition from libio532y.dlb[widechar.doj] will be used.]]></TEXT>
</MSG>
<MSG id='02093C60' mid='li2050' type='Warning' suppressed=''>
<TEXT><![CDATA[Symbol '_wmemset' is defined in more than one library.
        Defined in:     libio532y.dlb[widechar.doj]
        Redefined in:   libc532y.dlb[wmemset.doj]
        Definition from libio532y.dlb[widechar.doj] will be used.]]></TEXT>
</MSG>
<MSG id='02093ED8' mid='li2050' type='Warning' suppressed=''>
<TEXT><![CDATA[Symbol '_wprintf' is defined in more than one library.
        Defined in:     libio532y.dlb[widechar.doj]
        Redefined in:   libc532y.dlb[wprintf32.doj]
        Definition from libio532y.dlb[widechar.doj] will be used.]]></TEXT>
</MSG>
<MSG id='02094150' mid='li2050' type='Warning' suppressed=''>
<TEXT><![CDATA[Symbol '__wprintf64' is defined in more than one library.
        Defined in:     libio532y.dlb[widechar.doj]
        Redefined in:   libc532y.dlb[wprintf64.doj]
        Definition from libio532y.dlb[widechar.doj] will be used.]]></TEXT>
</MSG>
<MSG id='020943C8' mid='li2050' type='Warning' suppressed=''>
<TEXT><![CDATA[Symbol '_wscanf' is defined in more than one library.
        Defined in:     libio532y.dlb[widechar.doj]
        Redefined in:   libc532y.dlb[wscanf32.doj]
        Definition from libio532y.dlb[widechar.doj] will be used.]]></TEXT>
</MSG>
<MSG id='02094640' mid='li2050' type='Warning' suppressed=''>
<TEXT><![CDATA[Symbol '__wscanf64' is defined in more than one library.
        Defined in:     libio532y.dlb[widechar.doj]
        Redefined in:   libc532y.dlb[wscanf64.doj]
        Definition from libio532y.dlb[widechar.doj] will be used.]]></TEXT>
</MSG>
<MSG id='02094F60' mid='li2050' type='Warning' suppressed=''>
<TEXT><![CDATA[Symbol '__Files' is defined in more than one library.
        Defined in:     libio532y.dlb[xfiles.doj]
        Redefined in:   libc532y.dlb[xfiles.doj]
        Definition from libio532y.dlb[xfiles.doj] will be used.]]></TEXT>
</MSG>
<MSG id='020950C0' mid='li2050' type='Warning' suppressed=''>
<TEXT><![CDATA[Symbol '__Stderr' is defined in more than one library.
        Defined in:     libio532y.dlb[xfiles.doj]
        Redefined in:   libc532y.dlb[xfiles.doj]
        Definition from libio532y.dlb[xfiles.doj] will be used.]]></TEXT>
</MSG>
<MSG id='02095418' mid='li2050' type='Warning' suppressed=''>
<TEXT><![CDATA[Symbol '__Stdin' is defined in more than one library.
        Defined in:     libio532y.dlb[xfiles.doj]
        Redefined in:   libc532y.dlb[xfiles.doj]
        Definition from libio532y.dlb[xfiles.doj] will be used.]]></TEXT>
</MSG>
<MSG id='02095540' mid='li2050' type='Warning' suppressed=''>
<TEXT><![CDATA[Symbol '__Stdout' is defined in more than one library.
        Defined in:     libio532y.dlb[xfiles.doj]
        Redefined in:   libc532y.dlb[xfiles.doj]
        Definition from libio532y.dlb[xfiles.doj] will be used.]]></TEXT>
</MSG>
<MSG id='02096B68' mid='li2050' type='Warning' suppressed=''>
<TEXT><![CDATA[Symbol '__vector_table' is defined in more than one library.
        Defined in:     libsmall532y.dlb[xsignal_s.doj]
        Redefined in:   libc532y.dlb[xsignal.doj]
        Definition from libsmall532y.dlb[xsignal_s.doj] will be used.]]></TEXT>
</MSG>
<MSG id='02098D10' mid='li2050' type='Warning' suppressed=''>
<TEXT><![CDATA[Symbol '_raise_interrupt' is defined in more than one library.
        Defined in:     libsmall532y.dlb[raiseint_s.doj]
        Redefined in:   libevent532y.dlb[raiseint.doj]
        Definition from libsmall532y.dlb[raiseint_s.doj] will be used.]]></TEXT>
</MSG>
<MSG id='02099158' mid='li2050' type='Warning' suppressed=''>
<TEXT><![CDATA[Symbol '_register_handler' is defined in more than one library.
        Defined in:     libsmall532y.dlb[reghdlr_s.doj]
        Redefined in:   libevent532y.dlb[reghdlr.doj]
        Definition from libsmall532y.dlb[reghdlr_s.doj] will be used.]]></TEXT>
</MSG>
<MSG id='020A5048' mid='li2050' type='Warning' suppressed=''>
<TEXT><![CDATA[Symbol '___float32_to_float64' is defined in more than one library.
        Defined in:     libf64ieee532y.dlb[f32tof64.doj]
        Redefined in:   libsftflt532y.dlb[f32tof64.doj]
        Definition from libf64ieee532y.dlb[f32tof64.doj] will be used.]]></TEXT>
</MSG>
<MSG id='020A53D0' mid='li2050' type='Warning' suppressed=''>
<TEXT><![CDATA[Symbol '___float32_to_int32_round_to_zero' is defined in more than one library.
        Defined in:     libdsp532y.dlb[f32toi32z.doj]
        Redefined in:   libsftflt532y.dlb[f32toi32r.doj]
        Definition from libdsp532y.dlb[f32toi32z.doj] will be used.]]></TEXT>
</MSG>
<MSG id='020A5760' mid='li2050' type='Warning' suppressed=''>
<TEXT><![CDATA[Symbol '___float64_to_float32' is defined in more than one library.
        Defined in:     libf64ieee532y.dlb[f64tof32.doj]
        Redefined in:   libsftflt532y.dlb[f64tof32.doj]
        Definition from libf64ieee532y.dlb[f64tof32.doj] will be used.]]></TEXT>
</MSG>
<MSG id='020A5A60' mid='li2050' type='Warning' suppressed=''>
<TEXT><![CDATA[Symbol '___float64_to_int32' is defined in more than one library.
        Defined in:     libf64ieee532y.dlb[f64toi32.doj]
        Redefined in:   libsftflt532y.dlb[f64toi32.doj]
        Definition from libf64ieee532y.dlb[f64toi32.doj] will be used.]]></TEXT>
</MSG>
<MSG id='020A5CD8' mid='li2050' type='Warning' suppressed=''>
<TEXT><![CDATA[Symbol '___float64_to_int32_round_to_zero' is defined in more than one library.
        Defined in:     libf64ieee532y.dlb[f64toi32z.doj]
        Redefined in:   libsftflt532y.dlb[f64toi32r.doj]
        Definition from libf64ieee532y.dlb[f64toi32z.doj] will be used.]]></TEXT>
</MSG>
<MSG id='020A5F88' mid='li2050' type='Warning' suppressed=''>
<TEXT><![CDATA[Symbol '___float32_cmp' is defined in more than one library.
        Defined in:     libdsp532y.dlb[fltcmp.doj]
        Redefined in:   libsftflt532y.dlb[fltcmp.doj]
        Definition from libdsp532y.dlb[fltcmp.doj] will be used.]]></TEXT>
</MSG>
<MSG id='020A6200' mid='li2050' type='Warning' suppressed=''>
<TEXT><![CDATA[Symbol '___float64_add' is defined in more than one library.
        Defined in:     libf64ieee532y.dlb[addfl64.doj]
        Redefined in:   libsftflt532y.dlb[fp64add.doj]
        Definition from libf64ieee532y.dlb[addfl64.doj] will be used.]]></TEXT>
</MSG>
<MSG id='020A6478' mid='li2050' type='Warning' suppressed=''>
<TEXT><![CDATA[Symbol '___float64_cmp' is defined in more than one library.
        Defined in:     libf64ieee532y.dlb[cmpfl64.doj]
        Redefined in:   libsftflt532y.dlb[fp64cmp.doj]
        Definition from libf64ieee532y.dlb[cmpfl64.doj] will be used.]]></TEXT>
</MSG>
<MSG id='020A66F0' mid='li2050' type='Warning' suppressed=''>
<TEXT><![CDATA[Symbol '___float64_div' is defined in more than one library.
        Defined in:     libf64ieee532y.dlb[divfl64.doj]
        Redefined in:   libsftflt532y.dlb[fp64div.doj]
        Definition from libf64ieee532y.dlb[divfl64.doj] will be used.]]></TEXT>
</MSG>
<MSG id='020A6A10' mid='li2050' type='Warning' suppressed=''>
<TEXT><![CDATA[Symbol '___float64_mul' is defined in more than one library.
        Defined in:     libf64ieee532y.dlb[mulfl64.doj]
        Redefined in:   libsftflt532y.dlb[fp64mult.doj]
        Definition from libf64ieee532y.dlb[mulfl64.doj] will be used.]]></TEXT>
</MSG>
<MSG id='020A6D70' mid='li2050' type='Warning' suppressed=''>
<TEXT><![CDATA[Symbol '___float64_sub' is defined in more than one library.
        Defined in:     libf64ieee532y.dlb[subfl64.doj]
        Redefined in:   libsftflt532y.dlb[fp64sub.doj]
        Definition from libf64ieee532y.dlb[subfl64.doj] will be used.]]></TEXT>
</MSG>
<MSG id='020A6FE8' mid='li2050' type='Warning' suppressed=''>
<TEXT><![CDATA[Symbol '___float32_add' is defined in more than one library.
        Defined in:     libdsp532y.dlb[fpadd.doj]
        Redefined in:   libsftflt532y.dlb[fpadd.doj]
        Definition from libdsp532y.dlb[fpadd.doj] will be used.]]></TEXT>
</MSG>
<MSG id='020A7260' mid='li2050' type='Warning' suppressed=''>
<TEXT><![CDATA[Symbol '___float32_div' is defined in more than one library.
        Defined in:     libdsp532y.dlb[fpdiv.doj]
        Redefined in:   libsftflt532y.dlb[fpdiv.doj]
        Definition from libdsp532y.dlb[fpdiv.doj] will be used.]]></TEXT>
</MSG>
<MSG id='020A7628' mid='li2050' type='Warning' suppressed=''>
<TEXT><![CDATA[Symbol '___float32_mul' is defined in more than one library.
        Defined in:     libdsp532y.dlb[fpmult.doj]
        Redefined in:   libsftflt532y.dlb[fpmult.doj]
        Definition from libdsp532y.dlb[fpmult.doj] will be used.]]></TEXT>
</MSG>
<MSG id='020A7988' mid='li2050' type='Warning' suppressed=''>
<TEXT><![CDATA[Symbol '___float32_sub' is defined in more than one library.
        Defined in:     libdsp532y.dlb[fpadd.doj]
        Redefined in:   libsftflt532y.dlb[fpsub.doj]
        Definition from libdsp532y.dlb[fpadd.doj] will be used.]]></TEXT>
</MSG>
<MSG id='020A7C00' mid='li2050' type='Warning' suppressed=''>
<TEXT><![CDATA[Symbol '___int32_to_float32' is defined in more than one library.
        Defined in:     libdsp532y.dlb[fltsif.doj]
        Redefined in:   libsftflt532y.dlb[i32tof32.doj]
        Definition from libdsp532y.dlb[fltsif.doj] will be used.]]></TEXT>
</MSG>
<MSG id='020A7E78' mid='li2050' type='Warning' suppressed=''>
<TEXT><![CDATA[Symbol '___int32_to_float64' is defined in more than one library.
        Defined in:     libf64ieee532y.dlb[i32tof64.doj]
        Redefined in:   libsftflt532y.dlb[i32tof64.doj]
        Definition from libf64ieee532y.dlb[i32tof64.doj] will be used.]]></TEXT>
</MSG>
<MSG id='020A8160' mid='li2050' type='Warning' suppressed=''>
<TEXT><![CDATA[Symbol '_isinf' is defined in more than one library.
        Defined in:     libdsp532y.dlb[isinf.doj]
        Redefined in:   libsftflt532y.dlb[isinf.doj]
        Definition from libdsp532y.dlb[isinf.doj] will be used.]]></TEXT>
</MSG>
<MSG id='020A83D8' mid='li2050' type='Warning' suppressed=''>
<TEXT><![CDATA[Symbol '_isnan' is defined in more than one library.
        Defined in:     libdsp532y.dlb[isnan.doj]
        Redefined in:   libsftflt532y.dlb[isnan.doj]
        Definition from libdsp532y.dlb[isnan.doj] will be used.]]></TEXT>
</MSG>
<MSG id='020A89A8' mid='li2050' type='Warning' suppressed=''>
<TEXT><![CDATA[Symbol '___unsigned_int32_to_float32' is defined in more than one library.
        Defined in:     libdsp532y.dlb[fltuif.doj]
        Redefined in:   libsftflt532y.dlb[u32tof32.doj]
        Definition from libdsp532y.dlb[fltuif.doj] will be used.]]></TEXT>
</MSG>
<MSG id='020A8C98' mid='li2050' type='Warning' suppressed=''>
<TEXT><![CDATA[Symbol '___unsigned_int32_to_float64' is defined in more than one library.
        Defined in:     libf64ieee532y.dlb[u32tof64.doj]
        Redefined in:   libsftflt532y.dlb[u32tof64.doj]
        Definition from libf64ieee532y.dlb[u32tof64.doj] will be used.]]></TEXT>
</MSG>
<MSG id='0213A6C8' mid='li2153' type='Warning' suppressed=''>
<TEXT><![CDATA[Input sections have inconsistent qualifiers as follows.
DOUBLEANY | .\Release\GPS_basiccrt.doj(.frt)
DOUBLEANY | .\Release\GPS_basiccrt.doj(.gdt)
DOUBLEANY | .\Release\GPS_basiccrt.doj(ctor)
DOUBLEANY | .\Release\GPS_basiccrt.doj(data1)
DOUBLEANY | .\Release\GPS_basiccrt.doj(program)
DOUBLE32  | .\Release\GPS_heaptab.doj(constdata)
DOUBLE32  | .\Release\GPS_heaptab.doj(data1)
DOUBLE32  | .\Release\GPS_heaptab.doj(program)
DOUBLE32  | .\Release\GPSMDMA.doj(bsz)
DOUBLE32  | .\Release\GPSMDMA.doj(constdata)
DOUBLE32  | .\Release\GPSMDMA.doj(data1)
DOUBLE32  | .\Release\GPSMDMA.doj(program)
DOUBLE32  | .\Release\image.doj(data1)
DOUBLE32  | .\Release\image.doj(program)
unknown   | .\Release\Reset_ADV.doj(L1_code)
DOUBLEANY | crtn532y.doj(.gdtl)
DOUBLEANY | crtn532y.doj(ctorl)
DOUBLEANY | cplbtab533.doj(cplb_data)
DOUBLEANY | libsmall532y.dlb[reghdlr_s.doj](program)
DOUBLEANY | libio532y.dlb[xprim.doj](program)
DOUBLEANY | libio532y.dlb[xprim.doj](voldata)
DOUBLEANY | libio532y.dlb[xprim_close.doj](data1)
DOUBLEANY | libio532y.dlb[xprim_close.doj](program)
DOUBLEANY | libio532y.dlb[xprim_open.doj](data1)
DOUBLEANY | libio532y.dlb[xprim_open.doj](program)
DOUBLEANY | libio532y.dlb[xprim_read.doj](data1)
DOUBLEANY | libio532y.dlb[xprim_read.doj](program)
DOUBLEANY | libio532y.dlb[xprim_write2.doj](data1)
DOUBLEANY | libio532y.dlb[xprim_write2.doj](program)
DOUBLEANY | libio532y.dlb[xprim_seek.doj](data1)
DOUBLEANY | libio532y.dlb[xprim_seek.doj](program)
DOUBLEANY | libio532y.dlb[devtab.doj](data1)
DOUBLEANY | libio532y.dlb[devtab.doj](program)
DOUBLEANY | libio532y.dlb[devIOtab.doj](bsz)
DOUBLEANY | libio532y.dlb[devIOtab.doj](program)
DOUBLEANY | libio532y.dlb[dev_drv_tab.doj](constdata)
DOUBLEANY | libio532y.dlb[dev_drv_tab.doj](data1)
DOUBLEANY | libio532y.dlb[dev_drv_tab.doj](program)
DOUBLEANY | libio532y.dlb[dev_init.doj](data1)
DOUBLEANY | libio532y.dlb[dev_init.doj](program)
DOUBLEANY | libio532y.dlb[primiolib.doj](data1)
DOUBLEANY | libio532y.dlb[primiolib.doj](program)
DOUBLEANY | libc532y.dlb[exit.doj](data1)
DOUBLEANY | libc532y.dlb[exit.doj](program)
DOUBLEANY | libc532y.dlb[exit_objects.doj](data1)
DOUBLEANY | libc532y.dlb[exit_objects.doj](program)
DOUBLEANY | libc532y.dlb[proccycles.doj](data1)
DOUBLEANY | libc532y.dlb[proccycles.doj](program)
DOUBLEANY | libc532y.dlb[_exit_s.doj](program)
DOUBLEANY | libevent532y.dlb[defhdlrs.doj](program)
DOUBLEANY | libevent532y.dlb[unknownex.doj](program)
DOUBLEANY | libcpp532y.dlb[ctorloop.doj](data1)
DOUBLEANY | libcpp532y.dlb[ctorloop.doj](program)
DOUBLEANY | libdsp532y.dlb[sdiv32.doj](program)
DOUBLEANY | libdsp532y.dlb[udiv32.doj](program)
DOUBLEANY | libdsp532y.dlb[lshfti64.doj](program)
DOUBLEANY | libdsp532y.dlb[muli64.doj](program)
DOUBLEANY | libdsp532y.dlb[udiv64.doj](program)
DOUBLEANY | libssl532y.dlb[adi_ebiu.doj](L1_data_a)
DOUBLEANY | libssl532y.dlb[adi_ebiu.doj](constdata)
DOUBLEANY | libssl532y.dlb[adi_ebiu.doj](data1)
DOUBLEANY | libssl532y.dlb[adi_ebiu.doj](program)
DOUBLEANY | libssl532y.dlb[adi_ebiu_asm.doj](L1_code)
DOUBLEANY | libssl532y.dlb[adi_ebiu_asm.doj](program)
DOUBLEANY | libssl532y.dlb[adi_int.doj](bsz)
DOUBLEANY | libssl532y.dlb[adi_int.doj](data1)
DOUBLEANY | libssl532y.dlb[adi_int.doj](program)
DOUBLEANY | libssl532y.dlb[adi_int_asm.doj](constdata)
DOUBLEANY | libssl532y.dlb[adi_int_asm.doj](program)
DOUBLEANY | libssl532y.dlb[adi_pwr.doj](bsz)
DOUBLEANY | libssl532y.dlb[adi_pwr.doj](constdata)
DOUBLEANY | libssl532y.dlb[adi_pwr.doj](data1)
DOUBLEANY | libssl532y.dlb[adi_pwr.doj](program)
DOUBLEANY | libssl532y.dlb[adi_pwr_asm.doj](L1_code)
DOUBLEANY | idle532mty.doj(program)
DOUBLEANY | librt_fileio532y.dlb[_memmove2.doj](data1)
DOUBLEANY | librt_fileio532y.dlb[_memmove2.doj](program)
DOUBLEANY | librt_fileio532y.dlb[argstring.doj](data1)
DOUBLEANY | librt_fileio532y.dlb[argstring.doj](program)
DOUBLEANY | librt_fileio532y.dlb[getargv.doj](bsz)
DOUBLEANY | librt_fileio532y.dlb[getargv.doj](data1)
DOUBLEANY | librt_fileio532y.dlb[getargv.doj](program)]]></TEXT>
</MSG>
<MSG id='02143358' mid='li3201' type='Informational' suppressed=''>
<TEXT><![CDATA[Successfully eliminated 7936 bytes in processor 'p0'
]]></TEXT>
<EXTENDED_INFO><![CDATA[Eliminated object (_heap_table, ._heap_table.end) of size 24 bytes from '.\Release\GPS_heaptab.doj(constdata)'
Eliminated object (_state, _state+0x4) of size 4 bytes from '.\Release\GPSMDMA.doj(data1)'
Eliminated object (0xea,0xec) of size 2 bytes from '.\Release\image.doj(program)'
Eliminated object (_vertLine, ._vertLine.end) of size 138 bytes from '.\Release\image.doj(program)'
Eliminated object (0x176,0x178) of size 2 bytes from '.\Release\image.doj(program)'
Eliminated object (_horLine, ._horLine.end) of size 86 bytes from '.\Release\image.doj(program)'
Eliminated object (_putPixel, ._putPixel.end) of size 66 bytes from '.\Release\image.doj(program)'
Eliminated object (_abs, ._abs.end) of size 10 bytes from '.\Release\image.doj(program)'
Eliminated object (0x376,0x378) of size 2 bytes from '.\Release\image.doj(program)'
Eliminated object (_line, ._line.end) of size 500 bytes from '.\Release\image.doj(program)'
Eliminated object (_rectangle, ._rectangle.end) of size 162 bytes from '.\Release\image.doj(program)'
Eliminated object (0x60e,0x610) of size 2 bytes from '.\Release\image.doj(program)'
Eliminated object (_rectangleFill, ._rectangleFill.end) of size 82 bytes from '.\Release\image.doj(program)'
Eliminated object (0x662,0x664) of size 2 bytes from '.\Release\image.doj(program)'
Eliminated object (_dcplbs_table, ._dcplbs_table.end) of size 300 bytes from 'cplbtab533.doj(cplb_data)'
Eliminated object (_icplbs_table, ._icplbs_table.end) of size 300 bytes from 'cplbtab533.doj(cplb_data)'
Eliminated object (__halt_processor, .__halt_processor.end) of size 4 bytes from 'idle532mty.doj(program)'
Eliminated object (__abort_processor, .__abort_processor.end) of size 4 bytes from 'idle532mty.doj(program)'
Eliminated object (_adi_ebiu_Terminate, ._adi_ebiu_Terminate.end) of size 14 bytes from 'libssl532y.dlb[adi_ebiu.doj](program)'
Eliminated object (_adi_ebiu_SaveConfig, ._adi_ebiu_SaveConfig.end) of size 106 bytes from 'libssl532y.dlb[adi_ebiu.doj](program)'
Eliminated object (0x23a,0x23c) of size 2 bytes from 'libssl532y.dlb[adi_ebiu.doj](program)'
Eliminated object (_adi_ebiu_GetConfigSize, ._adi_ebiu_GetConfigSize.end) of size 6 bytes from 'libssl532y.dlb[adi_ebiu.doj](program)'
Eliminated object (0x35a,0x35c) of size 2 bytes from 'libssl532y.dlb[adi_ebiu.doj](program)'
Eliminated object (_adi_ebiu_Reset, ._adi_ebiu_Reset.end) of size 70 bytes from 'libssl532y.dlb[adi_ebiu.doj](program)'
Eliminated object (0x7ee,0x7f0) of size 2 bytes from 'libssl532y.dlb[adi_ebiu.doj](program)'
Eliminated object (_adi_ebiu_LoadConfig, ._adi_ebiu_LoadConfig.end) of size 136 bytes from 'libssl532y.dlb[adi_ebiu.doj](program)'
Eliminated object (.epcrodata, .epcrodata.end) of size 32 bytes from 'libssl532y.dlb[adi_pwr.doj](constdata)'
Eliminated object (.SWITCH.0, .SWITCH.0.end) of size 100 bytes from 'libssl532y.dlb[adi_pwr.doj](constdata)'
Eliminated object (.SWITCH.2, .SWITCH.2.end) of size 24 bytes from 'libssl532y.dlb[adi_pwr.doj](constdata)'
Eliminated object (_ADI_ALLOWED_TRANSITIONS, ._ADI_ALLOWED_TRANSITIONS.end) of size 72 bytes from 'libssl532y.dlb[adi_pwr.doj](data1)'
Eliminated object (_adi_pwr_PowerSaving, ._adi_pwr_PowerSaving.end) of size 326 bytes from 'libssl532y.dlb[adi_pwr.doj](program)'
Eliminated object (_adi_pwr_Terminate, ._adi_pwr_Terminate.end) of size 14 bytes from 'libssl532y.dlb[adi_pwr.doj](program)'
Eliminated object (0x3de,0x3e0) of size 2 bytes from 'libssl532y.dlb[adi_pwr.doj](program)'
Eliminated object (0x502,0x504) of size 2 bytes from 'libssl532y.dlb[adi_pwr.doj](program)'
Eliminated object (_adi_pwr_GetPowerMode, ._adi_pwr_GetPowerMode.end) of size 68 bytes from 'libssl532y.dlb[adi_pwr.doj](program)'
Eliminated object (_adi_pwr_GetConfigSize, ._adi_pwr_GetConfigSize.end) of size 6 bytes from 'libssl532y.dlb[adi_pwr.doj](program)'
Eliminated object (0x54e,0x550) of size 2 bytes from 'libssl532y.dlb[adi_pwr.doj](program)'
Eliminated object (_adi_pwr_Control, ._adi_pwr_Control.end) of size 384 bytes from 'libssl532y.dlb[adi_pwr.doj](program)'
Eliminated object (_adi_pwr_GetPowerSaving, ._adi_pwr_GetPowerSaving.end) of size 60 bytes from 'libssl532y.dlb[adi_pwr.doj](program)'
Eliminated object (_adi_pwr_LoadConfig, ._adi_pwr_LoadConfig.end) of size 134 bytes from 'libssl532y.dlb[adi_pwr.doj](program)'
Eliminated object (0x80e,0x810) of size 2 bytes from 'libssl532y.dlb[adi_pwr.doj](program)'
Eliminated object (_adi_pwr_Reset, ._adi_pwr_Reset.end) of size 100 bytes from 'libssl532y.dlb[adi_pwr.doj](program)'
Eliminated object (_adi_pwr_SaveConfig, ._adi_pwr_SaveConfig.end) of size 86 bytes from 'libssl532y.dlb[adi_pwr.doj](program)'
Eliminated object (0x8ca,0x8cc) of size 2 bytes from 'libssl532y.dlb[adi_pwr.doj](program)'
Eliminated object (_adi_pwr_SetMaxFreqForVolt, ._adi_pwr_SetMaxFreqForVolt.end) of size 192 bytes from 'libssl532y.dlb[adi_pwr.doj](program)'
Eliminated object (0xbb6,0xbb8) of size 2 bytes from 'libssl532y.dlb[adi_pwr.doj](program)'
Eliminated object (_adi_pwr_AdjustFreq, ._adi_pwr_AdjustFreq.end) of size 160 bytes from 'libssl532y.dlb[adi_pwr.doj](program)'
Eliminated object (_adi_pwr_SetPowerMode, ._adi_pwr_SetPowerMode.end) of size 274 bytes from 'libssl532y.dlb[adi_pwr.doj](program)'
Eliminated object (___mulli3, .___mulli3.end) of size 106 bytes from 'libdsp532y.dlb[muli64.doj](program)'
Eliminated object (___udivdi3, .___udivdi3.end) of size 382 bytes from 'libdsp532y.dlb[udiv64.doj](program)'
Eliminated object (_adi_pwr_PLLProgrammingSequence, ._adi_pwr_PLLProgrammingSequence.end) of size 22 bytes from 'libssl532y.dlb[adi_pwr_asm.doj](L1_code)'
Eliminated object (_SavedIMask, _SavedIMask+0x4) of size 4 bytes from 'libssl532y.dlb[adi_int.doj](bsz)'
Eliminated object (_adi_int_InstanceData, ._adi_int_InstanceData.end) of size 264 bytes from 'libssl532y.dlb[adi_int.doj](bsz)'
Eliminated object (.epcdata, .epcdata.end) of size 12 bytes from 'libssl532y.dlb[adi_int.doj](data1)'
Eliminated object (_adi_int_GetLibraryDetails, ._adi_int_GetLibraryDetails.end) of size 24 bytes from 'libssl532y.dlb[adi_int.doj](program)'
Eliminated object (_adi_int_SICInterruptAsserted, ._adi_int_SICInterruptAsserted.end) of size 52 bytes from 'libssl532y.dlb[adi_int.doj](program)'
Eliminated object (0xb6,0xb8) of size 2 bytes from 'libssl532y.dlb[adi_int.doj](program)'
Eliminated object (_adi_int_SICSetIVG, ._adi_int_SICSetIVG.end) of size 64 bytes from 'libssl532y.dlb[adi_int.doj](program)'
Eliminated object (_adi_int_SICDisable, ._adi_int_SICDisable.end) of size 44 bytes from 'libssl532y.dlb[adi_int.doj](program)'
Eliminated object (_adi_int_SICEnable, ._adi_int_SICEnable.end) of size 40 bytes from 'libssl532y.dlb[adi_int.doj](program)'
Eliminated object (_adi_int_Init, ._adi_int_Init.end) of size 106 bytes from 'libssl532y.dlb[adi_int.doj](program)'
Eliminated object (_adi_int_EnterCriticalRegion, ._adi_int_EnterCriticalRegion.end) of size 34 bytes from 'libssl532y.dlb[adi_int.doj](program)'
Eliminated object (_adi_int_ExitCriticalRegion, ._adi_int_ExitCriticalRegion.end) of size 34 bytes from 'libssl532y.dlb[adi_int.doj](program)'
Eliminated object (0x1fa,0x1fc) of size 2 bytes from 'libssl532y.dlb[adi_int.doj](program)'
Eliminated object (_adi_int_SetIMaskBits, ._adi_int_SetIMaskBits.end) of size 74 bytes from 'libssl532y.dlb[adi_int.doj](program)'
Eliminated object (0x246,0x248) of size 2 bytes from 'libssl532y.dlb[adi_int.doj](program)'
Eliminated object (_adi_int_ClearIMaskBits, ._adi_int_ClearIMaskBits.end) of size 82 bytes from 'libssl532y.dlb[adi_int.doj](program)'
Eliminated object (0x29a,0x29c) of size 2 bytes from 'libssl532y.dlb[adi_int.doj](program)'
Eliminated object (_adi_int_CECHook, ._adi_int_CECHook.end) of size 224 bytes from 'libssl532y.dlb[adi_int.doj](program)'
Eliminated object (_adi_int_CECUnhook, ._adi_int_CECUnhook.end) of size 214 bytes from 'libssl532y.dlb[adi_int.doj](program)'
Eliminated object (0x452,0x454) of size 2 bytes from 'libssl532y.dlb[adi_int.doj](program)'
Eliminated object (_adi_int_Terminate, ._adi_int_Terminate.end) of size 112 bytes from 'libssl532y.dlb[adi_int.doj](program)'
Eliminated object (_adi_int_GetCurrentIVGLevel, ._adi_int_GetCurrentIVGLevel.end) of size 94 bytes from 'libssl532y.dlb[adi_int.doj](program)'
Eliminated object (__Atfuns, .__Atfuns.end) of size 160 bytes from 'libc532y.dlb[exit_objects.doj](data1)'
Eliminated object (___lshftli, .___lshftli.end) of size 100 bytes from 'libdsp532y.dlb[lshfti64.doj](program)'
Eliminated object (_adi_int_NestingISR, ._adi_int_NestingISR.end) of size 246 bytes from 'libssl532y.dlb[adi_int_asm.doj](program)'
Eliminated object (_adi_int_NonNestingISR, ._adi_int_NonNestingISR.end) of size 242 bytes from 'libssl532y.dlb[adi_int_asm.doj](program)'
Eliminated object (_adi_int_NestingEXC, ._adi_int_NestingEXC.end) of size 246 bytes from 'libssl532y.dlb[adi_int_asm.doj](program)'
Eliminated object (_adi_int_NonNestingEXC, ._adi_int_NonNestingEXC.end) of size 242 bytes from 'libssl532y.dlb[adi_int_asm.doj](program)'
Eliminated object (.adi_int_isrblock, .adi_int_isrblock.end) of size 512 bytes from 'libssl532y.dlb[adi_int_asm.doj](program)'
Eliminated object (___memmove2, .___memmove2.end) of size 118 bytes from 'librt_fileio532y.dlb[_memmove2.doj](program)'
]]></EXTENDED_INFO>
</MSG>
</DOCUMENT>
